{"cameraMode":{"drawMode":0,"name":"Shaded","section":"Shading Mode"},"sceneLighting":true,"audioPlay":false,"sceneViewState":{"m_AlwaysRefresh":false,"showFog":true,"showSkybox":true,"showFlares":true,"showImageEffects":true,"showParticleSystems":true,"showVisualEffectGraphs":true,"m_FxEnabled":true},"in2DMode":false,"pivot":{"x":648.1054077148438,"y":232.4066162109375,"z":-76.30919647216797},"rotation":{"x":0.016858795657753946,"y":0.06355290114879608,"z":0.00015286466805264354,"w":0.9983453750610352},"size":212.41954040527345,"orthographic":false}